{"is_source_file": true, "format": "bash", "description": "A shell script that detects and backs up various types of databases (SQLite, PostgreSQL, MySQL, MongoDB). It checks for the running database type and performs the corresponding backup command, saving backups to specified files.", "external_files": ["/usr/lib/postgresql/", "/var/run/mysqld/mysqld.sock"], "external_methods": ["ls", "cp", "sudo -u postgres pg_isready", "sudo mysqladmin ping", "mysqladmin ping", "mysql", "mysqldump", "sudo mysql", "mongosh", "mongodump"], "published": [], "classes": [], "methods": [], "calls": ["ls", "cp", "sudo -u postgres pg_isready", "mysqladmin ping", "mysqladmin ping", "mysql", "mysqldump", "sudo mysql", "mongosh", "mongodump"], "search-terms": ["backup_script", "database_backup", "SQLite", "PostgreSQL", "MySQL", "MongoDB", "database detection", "shell script"], "state": 2, "file_id": 6, "knowledge_revision": 14, "git_revision": "80dbac77966e76a4b1876e099e245303e2e44b0b", "hash": "d7da372b768c895a33088027314656c3", "format-version": 4, "code-base-name": "tasks_database", "filename": "tasks_database/backup_db.sh", "revision_history": [{"14": "80dbac77966e76a4b1876e099e245303e2e44b0b"}]}